{
  "layers":["jigs","core","network","nodes","os","clients","services","apps", "hide"],
  "crowbar-admin-node":"core",
  "crowbar-managed-node":"nodes",
  "crowbar-installed-node":"hide",
  "chef-server":"jigs",
  "chef-client":"jigs",
  "provisioner-os-install":"os",
  "network-server":"network",
  "network-admin":"network",
  "network-private":"network",
  "network-storage":"network",
  "network-public":"network",
  "bmc-nat-client":"nodes",
  "bmc-nat-router":"core",
  "deployer-client":"os",
  "dns-server":"core",
  "dns-database":"hide",
  "dns-client":"clients",
  "ntp-server": "core",
  "ntp-client": "clients",
  "provisioner-server":"core",
  "provisioner-repos":"core",
  "provisioner-dhcp-server":"core",
  "provisioner-dhcp-database":"hide",
  "logging-server":"core",
  "logging-client":"clients",
  "test-admin":"jigs",
  "test-server":"core",
  "test-client":"clients", 
  "test-discovery":"nodes",
  "test-library":"os",
  "test-fails":"hide",
  "test-event":"services",
  "ceph-config":"hide",
  "ceph-mon":"services",
  "ceph-osd":"services",
  "ceph-client":"apps"  
}